{
  "hash": "1b129030",
  "configHash": "bc1a8211",
  "lockfileHash": "01d2f08e",
  "browserHash": "e6008fe9",
  "optimized": {
    "@element-plus/icons-vue": {
      "src": "../../../../../node_modules/@element-plus/icons-vue/dist/index.js",
      "file": "@element-plus_icons-vue.js",
      "fileHash": "673b1595",
      "needsInterop": false
    },
    "axios": {
      "src": "../../../../../node_modules/axios/index.js",
      "file": "axios.js",
      "fileHash": "6c43bd9a",
      "needsInterop": false
    },
    "echarts": {
      "src": "../../../../../node_modules/echarts/index.js",
      "file": "echarts.js",
      "fileHash": "fbe9e222",
      "needsInterop": false
    },
    "element-plus": {
      "src": "../../../../../node_modules/element-plus/es/index.mjs",
      "file": "element-plus.js",
      "fileHash": "0465d8ca",
      "needsInterop": false
    }
  },
  "chunks": {
    "chunk-2YKGTGVD": {
      "file": "chunk-2YKGTGVD.js"
    },
    "chunk-MNTBHR2J": {
      "file": "chunk-MNTBHR2J.js"
    }
  }
}